linky_tools-1.0.0.data/scripts/linky_grabber.py
linky_tools-1.0.0.data/scripts/linky_query.py
linkydb/__init__.py
linkydb/db.py
linkydb/models.py
linky_tools-1.0.0.dist-info/LICENSE
linky_tools-1.0.0.dist-info/METADATA
linky_tools-1.0.0.dist-info/WHEEL
linky_tools-1.0.0.dist-info/top_level.txt
linky_tools-1.0.0.dist-info/RECORD
