Metadata-Version: 2.1
Name: linky-tools
Version: 1.0.0
Summary: Provide tools to grab and query data generated by Enedis Linky smart meter
Home-page: https://gitlab.com/ermitz/linky-tools
Author: ermitz
Author-email: ermitz888@gmail.com
License: UNKNOWN
Platform: UNKNOWN
Classifier: Programming Language :: Python
Classifier: License :: OSI Approved :: GNU General Public License v3 or later (GPLv3+)
Classifier: Natural Language :: English
Classifier: Operating System :: OS Independent
Classifier: Programming Language :: Python :: 3.5
Classifier: Programming Language :: Python :: 3.6
Classifier: Topic :: Home Automation
Requires-Dist: linkymeter (==1.0.0)
Requires-Dist: pony (==0.7.9)
Requires-Dist: python-dateutil (==2.7.5)
Requires-Dist: requests (==2.21.0)
